propfinder/__init__.py
propfinder/events.py
propfinder/pshell.py
propfinder/render.py
propfinder/resources.py
propfinder/routes.py
propfinder/security.py
propfinder/tests.py
propfinder/translations.py
propfinder/alembic/script.py.mako
propfinder/alembic/versions/README.txt
propfinder/models/__init__.py
propfinder/models/itemmixin.py
propfinder/models/location.py
propfinder/models/meta.py
propfinder/models/property.py
propfinder/models/stats.py
propfinder/models/url.py
propfinder/models/user.py
propfinder/schemas/__init__.py
propfinder/schemas/location.py
propfinder/schemas/property.py
propfinder/schemas/stats.py
propfinder/schemas/url.py
propfinder/schemas/user.py
propfinder/scripts/__init__.py
propfinder/scripts/deactivate_properties.py
propfinder/scripts/initialize_db.py
propfinder/scripts/scrape_properties.py
propfinder/scripts/update_stats.py
propfinder/static/chartjs/dist/Chart.bundle.js
propfinder/static/chartjs/dist/Chart.bundle.min.js
propfinder/static/chartjs/dist/Chart.css
propfinder/static/chartjs/dist/Chart.js
propfinder/static/chartjs/dist/Chart.min.css
propfinder/static/chartjs/dist/Chart.min.js
propfinder/static/css/main.css
propfinder/static/font-awesome/LICENSE.txt
propfinder/static/font-awesome/css/all.css
propfinder/static/font-awesome/css/all.min.css
propfinder/static/font-awesome/css/brands.css
propfinder/static/font-awesome/css/brands.min.css
propfinder/static/font-awesome/css/fontawesome.css
propfinder/static/font-awesome/css/fontawesome.min.css
propfinder/static/font-awesome/css/regular.css
propfinder/static/font-awesome/css/regular.min.css
propfinder/static/font-awesome/css/solid.css
propfinder/static/font-awesome/css/solid.min.css
propfinder/static/font-awesome/css/svg-with-js.css
propfinder/static/font-awesome/css/svg-with-js.min.css
propfinder/static/font-awesome/css/v4-shims.css
propfinder/static/font-awesome/css/v4-shims.min.css
propfinder/static/font-awesome/js/all.js
propfinder/static/font-awesome/js/all.min.js
propfinder-0.1.0.dist-info/METADATA
propfinder-0.1.0.dist-info/WHEEL
propfinder-0.1.0.dist-info/entry_points.txt
propfinder-0.1.0.dist-info/top_level.txt
propfinder-0.1.0.dist-info/RECORD
