Metadata-Version: 2.1
Name: propfinder
Version: 0.1.0
Summary: propfinder
Home-page: UNKNOWN
Author: 
Author-email: 
License: UNKNOWN
Keywords: web pyramid pylons
Platform: UNKNOWN
Classifier: Programming Language :: Python
Classifier: Framework :: Pyramid
Classifier: Topic :: Internet :: WWW/HTTP
Classifier: Topic :: Internet :: WWW/HTTP :: WSGI :: Application
Requires-Dist: plaster-pastedeploy
Requires-Dist: pyramid
Requires-Dist: pyramid-beaker
Requires-Dist: pyramid-chameleon
Requires-Dist: pyramid-debugtoolbar
Requires-Dist: waitress
Requires-Dist: alembic
Requires-Dist: pyramid-retry
Requires-Dist: pyramid-tm
Requires-Dist: SQLAlchemy
Requires-Dist: transaction
Requires-Dist: zope.sqlalchemy
Requires-Dist: requests
Requires-Dist: beautifulsoup4
Requires-Dist: simplejson
Requires-Dist: statistics
Requires-Dist: propscraper
Provides-Extra: testing
Requires-Dist: WebTest (>=1.3.1) ; extra == 'testing'
Requires-Dist: pytest (>=3.7.4) ; extra == 'testing'
Requires-Dist: pytest-cov ; extra == 'testing'
